wordslab_notebooks_lib/__init__.py
wordslab_notebooks_lib/_modidx.py
wordslab_notebooks_lib/chat.py
wordslab_notebooks_lib/core.py
wordslab_notebooks_lib/env.py
wordslab_notebooks_lib/notebook.py
wordslab_notebooks_lib/tools.py
wordslab_notebooks_lib/labextension/package.json
wordslab_notebooks_lib/labextension/schemas/wordslab-notebooks-lib/package.json.orig
wordslab_notebooks_lib/labextension/schemas/wordslab-notebooks-lib/plugin.json
wordslab_notebooks_lib/labextension/static/509.dc8f2aa8db85e628bc4a.js
wordslab_notebooks_lib/labextension/static/665.8b93fe8d79c1bb155edc.js
wordslab_notebooks_lib/labextension/static/remoteEntry.f4eea04c75b262d7af88.js
wordslab_notebooks_lib/labextension/static/style.js
wordslab_notebooks_lib/labextension/static/third-party-licenses.json
wordslab_notebooks_lib-0.0.16.data/data/share/jupyter/labextensions/wordslab-notebooks-lib/install.json
wordslab_notebooks_lib-0.0.16.data/data/share/jupyter/labextensions/wordslab-notebooks-lib/package.json
wordslab_notebooks_lib-0.0.16.data/data/share/jupyter/labextensions/wordslab-notebooks-lib/schemas/wordslab-notebooks-lib/package.json.orig
wordslab_notebooks_lib-0.0.16.data/data/share/jupyter/labextensions/wordslab-notebooks-lib/schemas/wordslab-notebooks-lib/plugin.json
wordslab_notebooks_lib-0.0.16.data/data/share/jupyter/labextensions/wordslab-notebooks-lib/static/509.dc8f2aa8db85e628bc4a.js
wordslab_notebooks_lib-0.0.16.data/data/share/jupyter/labextensions/wordslab-notebooks-lib/static/665.8b93fe8d79c1bb155edc.js
wordslab_notebooks_lib-0.0.16.data/data/share/jupyter/labextensions/wordslab-notebooks-lib/static/remoteEntry.f4eea04c75b262d7af88.js
wordslab_notebooks_lib-0.0.16.data/data/share/jupyter/labextensions/wordslab-notebooks-lib/static/style.js
wordslab_notebooks_lib-0.0.16.data/data/share/jupyter/labextensions/wordslab-notebooks-lib/static/third-party-licenses.json
wordslab_notebooks_lib-0.0.16.dist-info/licenses/LICENSE
wordslab_notebooks_lib-0.0.16.dist-info/METADATA
wordslab_notebooks_lib-0.0.16.dist-info/WHEEL
wordslab_notebooks_lib-0.0.16.dist-info/entry_points.txt
wordslab_notebooks_lib-0.0.16.dist-info/top_level.txt
wordslab_notebooks_lib-0.0.16.dist-info/RECORD
