Metadata-Version: 2.4
Name: wordslab-notebooks-lib
Version: 0.0.16
Summary: Python library to help with AI usage in wordslab-notebooks
Home-page: https://github.com/wordslab-org/wordslab-notebooks-lib
Author: Laurent Prud'hon
Author-email: laurent.prudhon@hotmail.fr
License: Apache Software License 2.0
Keywords: wordslab wordslab-notebooks ai jupyter jupyterlab notebook python
Classifier: Framework :: Jupyter
Classifier: Framework :: Jupyter :: JupyterLab
Classifier: Framework :: Jupyter :: JupyterLab :: 4
Classifier: Framework :: Jupyter :: JupyterLab :: Extensions
Classifier: Framework :: Jupyter :: JupyterLab :: Extensions :: Prebuilt
Classifier: License :: OSI Approved :: Apache Software License
Classifier: Programming Language :: Python
Classifier: Programming Language :: Python :: 3
Classifier: Programming Language :: Python :: 3.10
Classifier: Programming Language :: Python :: 3.11
Classifier: Programming Language :: Python :: 3.12
Classifier: Programming Language :: Python :: 3.13
Classifier: Programming Language :: Python :: 3.14
Requires-Python: >=3.10
License-File: LICENSE
Requires-Dist: ipykernel
Requires-Dist: nbformat
Requires-Dist: fastcore>=1.9.8
Requires-Dist: toolslm>=0.3.13
Requires-Dist: ollama>=0.6.1
Requires-Dist: openai>=2.11.0
Requires-Dist: beautifulsoup4
Requires-Dist: cloudscraper
Requires-Dist: html2text
Requires-Dist: lxml
Provides-Extra: dev
Dynamic: author
Dynamic: author-email
Dynamic: description
Dynamic: description-content-type
Dynamic: home-page
Dynamic: keywords
Dynamic: license
Dynamic: license-file
Dynamic: provides-extra
Dynamic: requires-dist
Dynamic: requires-python
Dynamic: summary
